oneqloud-client/__init__.py
oneqloud-client/client.py
oneqloud-client/qbit_pb2.py
oneqloud-client/qbit_pb2_grpc.py
oneqloud_client/__init__.py
oneqloud_client/ca.pem
oneqloud_client/client.py
oneqloud_client/qbit_pb2.py
oneqloud_client/qbit_pb2_grpc.py
oneqloud_client-0.2.15.dist-info/METADATA
oneqloud_client-0.2.15.dist-info/WHEEL
oneqloud_client-0.2.15.dist-info/top_level.txt
oneqloud_client-0.2.15.dist-info/RECORD
